cosdata/client.py
cosdata/collection.py
cosdata/index.py
cosdata/transaction.py
cosdata-0.1.2.dist-info/licenses/LICENSE
cosdata-0.1.2.dist-info/METADATA
cosdata-0.1.2.dist-info/WHEEL
cosdata-0.1.2.dist-info/top_level.txt
cosdata-0.1.2.dist-info/RECORD
