Metadata-Version: 2.4
Name: cosdata
Version: 0.1.2
Summary: Python client for Cosdata Vector Database
Author-email: Cosdata <contact@cosdata.io>
License:                                  Apache License
Project-URL: Homepage, https://github.com/cosdata/cosdata-sdk-python
Project-URL: Bug Tracker, https://github.com/cosdata/cosdata-sdk-python/issues
Project-URL: Documentation, https://docs.cosdata.io
Classifier: Development Status :: 4 - Beta
Classifier: Intended Audience :: Developers
Classifier: License :: OSI Approved :: Apache Software License
Classifier: Programming Language :: Python :: 3
Classifier: Programming Language :: Python :: 3.7
Classifier: Programming Language :: Python :: 3.8
Classifier: Programming Language :: Python :: 3.9
Classifier: Programming Language :: Python :: 3.10
Classifier: Programming Language :: Python :: 3.11
Classifier: Topic :: Database
Classifier: Topic :: Scientific/Engineering :: Artificial Intelligence
Requires-Python: >=3.7
License-File: LICENSE
Requires-Dist: numpy>=1.21.0
Requires-Dist: requests<3.0.0,>=2.28.0
Provides-Extra: dev
Requires-Dist: pytest>=6.0; extra == "dev"
Requires-Dist: black>=23.0.0; extra == "dev"
Requires-Dist: isort>=5.10.0; extra == "dev"
Requires-Dist: mypy>=0.991; extra == "dev"
Provides-Extra: docs
Requires-Dist: mkdocs>=1.4.0; extra == "docs"
Requires-Dist: mkdocs-material>=8.5.0; extra == "docs"
Requires-Dist: mkdocstrings>=0.19.0; extra == "docs"
Requires-Dist: mkdocstrings-python>=0.8.0; extra == "docs"
Dynamic: license-file
